lvpyio/__init__.py
lvpyio/io/Core.Buffer.dll
lvpyio/io/Core.Common.dll
lvpyio/io/Core.DataObjects.dll
lvpyio/io/Core.Set.dll
lvpyio/io/IOCompact.dll
lvpyio/io/LaVision.Logging.dll
lvpyio/io/LaVision.Utils.dll
lvpyio/io/Qt5Core.dll
lvpyio/io/__init__.py
lvpyio/io/attribute.cp312-win_amd64.pyd
lvpyio/io/component.cp312-win_amd64.pyd
lvpyio/io/grid.cp312-win_amd64.pyd
lvpyio/io/particles.cp312-win_amd64.pyd
lvpyio/io/plane.cp312-win_amd64.pyd
lvpyio/io/pugixml.dll
lvpyio/io/read_buffer.cp312-win_amd64.pyd
lvpyio/io/scale.cp312-win_amd64.pyd
lvpyio/io/set.cp312-win_amd64.pyd
lvpyio/io/type_mapper.cp312-win_amd64.pyd
lvpyio/io/write_buffer.cp312-win_amd64.pyd
lvpyio/io/zlibwapi.dll
lvpyio/types/__init__.py
lvpyio/types/buffer.py
lvpyio/types/component.py
lvpyio/types/frame.py
lvpyio/types/grid.py
lvpyio/types/particles.py
lvpyio/types/plot_utils.py
lvpyio/types/scale.py
lvpyio/types/set_utils.py
lvpyio/validate/__init__.py
lvpyio/validate/validate_array.py
lvpyio/validate/validate_attributes.py
lvpyio/validate/validate_buffer.py
lvpyio/validate/validate_common.py
lvpyio/validate/validate_particles.py
lvpyio/version/__init__.py
lvpyio/version/dll_version.txt
lvpyio/version/version.txt
lvpyio-1.3.1.dist-info/LICENSE.txt
lvpyio-1.3.1.dist-info/LICENSE_pugixml.txt
lvpyio-1.3.1.dist-info/LICENSE_qt.txt
lvpyio-1.3.1.dist-info/LICENSE_zlib.txt
lvpyio-1.3.1.dist-info/METADATA
lvpyio-1.3.1.dist-info/WHEEL
lvpyio-1.3.1.dist-info/top_level.txt
lvpyio-1.3.1.dist-info/RECORD
