Metadata-Version: 2.1
Name: lvpyio
Version: 1.3.1
Summary: A reader/writer for DaVis images, vector fields, and particle fields
Home-page: https://www.lavision.de/
Author: LaVision GmbH
Author-email: python@lavision.de
License: Free To Use But Restricted
Platform: Windows
Platform: Linux
License-File: LICENSE.txt
License-File: ThirdPartyLicenses/LICENSE_pugixml.txt
License-File: ThirdPartyLicenses/LICENSE_qt.txt
License-File: ThirdPartyLicenses/LICENSE_zlib.txt
Requires-Dist: numpy>=2.0.0
Provides-Extra: plotting
Requires-Dist: matplotlib>=3.2.1; extra == "plotting"
